Workbook

Sheet Summary
A1: TỔNG KẾT & KỊCH BẢN v1.1
A3: Chỉ số | B3: Q1 | C3: Q2 | D3: Q3 | E3: Q4 | F3: Năm 1
A4: Doanh thu (net) | B4: =SUM(Model!B23:D23) -> 7087 | C4: =SUM(Model!E23:G23) -> 22028.667 | D4: =SUM(Model!H23:J23) -> 37813.667 | E4: =SUM(Model!K23:M23) -> 56027.667 | F4: =SUM(B4:E4) -> 122957
A5: Chi phí | B5: =SUM(Model!B32:D32) -> 13454.35 | C5: =SUM(Model!E32:G32) -> 13401.433 | D5: =SUM(Model!H32:J32) -> 17190.683 | E5: =SUM(Model!K32:M32) -> 20501.383 | F5: =SUM(B5:E5) -> 64547.85
A6: Lợi nhuận | B6: =B4-B5 -> -6367.35 | C6: =C4-C5 -> 8627.2333 | D6: =D4-D5 -> 20622.983 | E6: =E4-E5 -> 35526.283 | F6: =F4-F5 -> 58409.15
A8: KỊCH BẢN (Năm 1) | B8: Hệ số | C8: Doanh thu | D8: Lợi nhuận
A9: Pessimistic | B9: 0.6 | C9: =$F$4*B9 -> 73774.2 | D9: =$F$4*B9-$F$5 -> 9226.35
A10: Conservative (base) | B10: 1 | C10: =$F$4*B10 -> 122957 | D10: =$F$4*B10-$F$5 -> 58409.15
A11: Optimistic | B11: 1.3 | C11: =$F$4*B11 -> 159844.1 | D11: =$F$4*B11-$F$5 -> 95296.25
A13: ROI trên vốn <15M (base) | B13: =F6/15000 -> 3.8939433
A14: Break-even dòng tiền | B14: M6-M7

Sheet Assumptions
A1: EcoPickle Connect — Cashflow Model v1.1 (điều chỉnh pricing)
A2: Ô XANH = input chỉnh được. Coach/Chủ sân đăng ký & setup MIỄN PHÍ. Dạy học CHƯA thu phí.
A4: KEY PRICES / TAKE-RATES
A5: Average sale price (k) | B5: 2000 | C5: Giá bán TB (D2)
A6: Sales commission % | B6: 0.08 | C6: BR-CONS-007
A7: Rental net blended /lượt (k) | B7: 130 | C7: sau hoàn phí khi mua
A8: Certification fee (k) | B8: 149 | C8: C2C upgrade / pivot
A9: C2C listing fee (k) | B9: 19 | C9: tin thứ 3+
A10: Vendor net /vendor/tháng (k) | B10: 360 | C10: rev-share+boost
A11: Tournament pkg — 1 tháng (k) | B11: 150 | C11: gói lẻ
A12: Tournament pkg — 6 tháng (k) | B12: 600 | C12: ≈100k/tháng
A13: Tournament pkg — 12 tháng (k) | B13: 1000 | C13: ≈83k/tháng
A14: Tournament pkg — eff /sub/tháng (k) | B14: 110 | C14: blended mix gói
A15: Court Owner value acct /năm (k) | B15: 1000 | C15: ≈83k/tháng recognized
A16: Trainer lesson fee | B16: CHƯA | C16: học viên tự book — add-on nghiên cứu sau

Sheet Model
A1: MONTHLY CASHFLOW MODEL v1.1
A3: Dòng / Tháng | B3: M1 | C3: M2 | D3: M3 | E3: M4 | F3: M5 | G3: M6 | H3: M7 | I3: M8 | J3: M9 | K3: M10 | L3: M11 | M3: M12 | N3: Năm 1
A5: KHỐI LƯỢNG (input)
A6: Rentals/tháng | B6: 6 | C6: 12 | D6: 18 | E6: 26 | F6: 32 | G6: 40 | H6: 46 | I6: 52 | J6: 60 | K6: 66 | L6: 72 | M6: 85 | N6: =SUM(B6:M6) -> 515
A7: Sales/tháng | B7: 2 | C7: 3 | D7: 5 | E7: 6 | F7: 8 | G7: 10 | H7: 11 | I7: 13 | J7: 15 | K7: 17 | L7: 20 | M7: 24 | N7: =SUM(B7:M7) -> 134
A8: Certifications/tháng | B8: 0 | C8: 1 | D8: 2 | E8: 3 | F8: 5 | G8: 6 | H8: 8 | I8: 10 | J8: 12 | K8: 14 | L8: 16 | M8: 18 | N8: =SUM(B8:M8) -> 95
A9: C2C paid listings/tháng | B9: 0 | C9: 0 | D9: 0 | E9: 5 | F9: 8 | G9: 11 | H9: 16 | I9: 21 | J9: 26 | K9: 32 | L9: 37 | M9: 42 | N9: =SUM(B9:M9) -> 198
A10: Active vendors | B10: 0 | C10: 0 | D10: 1 | E10: 2 | F10: 2 | G10: 3 | H10: 3 | I10: 4 | J10: 4 | K10: 4 | L10: 5 | M10: 5 | N10: =SUM(B10:M10) -> 33
A11: Tournament-pkg subs (coach+sân) | B11: 0 | C11: 0 | D11: 0 | E11: 0 | F11: 0 | G11: 2 | H11: 2 | I11: 3 | J11: 4 | K11: 5 | L11: 7 | M11: 9 | N11: =SUM(B11:M11) -> 32
A12: Court Owner value accounts | B12: 0 | C12: 0 | D12: 0 | E12: 0 | F12: 1 | G12: 1 | H12: 1 | I12: 2 | J12: 2 | K12: 2 | L12: 3 | M12: 3 | N12: =SUM(B12:M12) -> 15
A13: Active trainers (free) | B13: 2 | C13: 3 | D13: 4 | E13: 5 | F13: 6 | G13: 8 | H13: 9 | I13: 10 | J13: 11 | K13: 12 | L13: 13 | M13: 14 | N13: =SUM(B13:M13) -> 97
A14: DOANH THU (net, k)
A15: R1 Commission | B15: =B7*Assumptions!$B$5*Assumptions!$B$6 -> 320 | C15: =C7*Assumptions!$B$5*Assumptions!$B$6 -> 480 | D15: =D7*Assumptions!$B$5*Assumptions!$B$6 -> 800 | E15: =E7*Assumptions!$B$5*Assumptions!$B$6 -> 960 | F15: =F7*Assumptions!$B$5*Assumptions!$B$6 -> 1280 | G15: =G7*Assumptions!$B$5*Assumptions!$B$6 -> 1600 | H15: =H7*Assumptions!$B$5*Assumptions!$B$6 -> 1760 | I15: =I7*Assumptions!$B$5*Assumptions!$B$6 -> 2080 | ... M15: =M7*Assumptions!$B$5*Assumptions!$B$6 -> 3840 | N15: =SUM(B15:M15) -> 21440
A16: R2 Rental (net) | B16: =B6*Assumptions!$B$7 -> 780 | C16: =C6*Assumptions!$B$7 -> 1560 | D16: =D6*Assumptions!$B$7 -> 2340 | E16: =E6*Assumptions!$B$7 -> 3380 | F16: =F6*Assumptions!$B$7 -> 4160 | G16: =G6*Assumptions!$B$7 -> 5200 | H16: =H6*Assumptions!$B$7 -> 5980 | I16: =I6*Assumptions!$B$7 -> 6760 | ... M16: =M6*Assumptions!$B$7 -> 11050 | N16: =SUM(B16:M16) -> 66950
A17: R3 Certification | B17: =B8*Assumptions!$B$8 -> 0 | C17: =C8*Assumptions!$B$8 -> 149 | D17: =D8*Assumptions!$B$8 -> 298 | E17: =E8*Assumptions!$B$8 -> 447 | F17: =F8*Assumptions!$B$8 -> 745 | G17: =G8*Assumptions!$B$8 -> 894 | H17: =H8*Assumptions!$B$8 -> 1192 | I17: =I8*Assumptions!$B$8 -> 1490 | ... M17: =M8*Assumptions!$B$8 -> 2682 | N17: =SUM(B17:M17) -> 14155
A18: R4 C2C listing | B18: =B9*Assumptions!$B$9 -> 0 | C18: =C9*Assumptions!$B$9 -> 0 | D18: =D9*Assumptions!$B$9 -> 0 | E18: =E9*Assumptions!$B$9 -> 95 | F18: =F9*Assumptions!$B$9 -> 152 | G18: =G9*Assumptions!$B$9 -> 209 | H18: =H9*Assumptions!$B$9 -> 304 | I18: =I9*Assumptions!$B$9 -> 399 | ... M18: =M9*Assumptions!$B$9 -> 798 | N18: =SUM(B18:M18) -> 3762
A19: R5 Vendor rev-share+boost | B19: =B10*Assumptions!$B$10 -> 0 | C19: =C10*Assumptions!$B$10 -> 0 | D19: =D10*Assumptions!$B$10 -> 360 | E19: =E10*Assumptions!$B$10 -> 720 | F19: =F10*Assumptions!$B$10 -> 720 | G19: =G10*Assumptions!$B$10 -> 1080 | H19: =H10*Assumptions!$B$10 -> 1080 | I19: =I10*Assumptions!$B$10 -> 1440 | ... M19: =M10*Assumptions!$B$10 -> 1800 | N19: =SUM(B19:M19) -> 11880
A20: R6 Tournament package | B20: =B11*Assumptions!$B$14 -> 0 | C20: =C11*Assumptions!$B$14 -> 0 | D20: =D11*Assumptions!$B$14 -> 0 | E20: =E11*Assumptions!$B$14 -> 0 | F20: =F11*Assumptions!$B$14 -> 0 | G20: =G11*Assumptions!$B$14 -> 220 | H20: =H11*Assumptions!$B$14 -> 220 | I20: =I11*Assumptions!$B$14 -> 330 | ... M20: =M11*Assumptions!$B$14 -> 990 | N20: =SUM(B20:M20) -> 3520
A21: R7 Court Owner value acct | B21: =B12*Assumptions!$B$15/12 -> 0 | C21: =C12*Assumptions!$B$15/12 -> 0 | D21: =D12*Assumptions!$B$15/12 -> 0 | E21: =E12*Assumptions!$B$15/12 -> 0 | F21: =F12*Assumptions!$B$15/12 -> 83.333333 | G21: =G12*Assumptions!$B$15/12 -> 83.333333 | H21: =H12*Assumptions!$B$15/12 -> 83.333333 | I21: =I12*Assumptions!$B$15/12 -> 166.66667 | ... M21: =M12*Assumptions!$B$15/12 -> 250 | N21: =SUM(B21:M21) -> 1250
A22: R8 Trainer lessons (CHƯA thu) | B22: 0 | C22: 0 | D22: 0 | E22: 0 | F22: 0 | G22: 0 | H22: 0 | I22: 0 | J22: 0 | K22: 0 | L22: 0 | M22: 0 | N22: =SUM(B22:M22) -> 0
A23: TỔNG DOANH THU | B23: =SUM(B15:B22) -> 1100 | C23: =SUM(C15:C22) -> 2189 | D23: =SUM(D15:D22) -> 3798 | E23: =SUM(E15:E22) -> 5602 | F23: =SUM(F15:F22) -> 7140.3333 | G23: =SUM(G15:G22) -> 9286.3333 | H23: =SUM(H15:H22) -> 10619.333 | I23: =SUM(I15:I22) -> 12665.667 | ... M23: =SUM(M15:M22) -> 21410 | N23: =SUM(B23:M23) -> 122957
A24: CHI PHÍ (k)
A25: Tech | B25: 300 | C25: 300 | D25: 500 | E25: 500 | F25: 700 | G25: 700 | H25: 700 | I25: 700 | J25: 900 | K25: 900 | L25: 900 | M25: 900 | N25: =SUM(B25:M25) -> 8000
A26: Marketing | B26: 500 | C26: 500 | D26: 800 | E26: 800 | F26: 1000 | G26: 1000 | H26: 1000 | I26: 1000 | J26: 1500 | K26: 1500 | L26: 1500 | M26: 1500 | N26: =SUM(B26:M26) -> 12600
A27: Runner part-time | B27: 0 | C27: 0 | D27: 1200 | E27: 1200 | F27: 1500 | G27: 1500 | H27: 1500 | I27: 1500 | J27: 1800 | K27: 1800 | L27: 1800 | M27: 1800 | N27: =SUM(B27:M27) -> 15600
A28: Moderation part-time | B28: 0 | C28: 0 | D28: 0 | E28: 0 | F28: 1000 | G28: 1000 | H28: 1000 | I28: 1000 | J28: 1000 | K28: 1000 | L28: 1000 | M28: 1000 | N28: =SUM(B28:M28) -> 8000
A29: Consumables | B29: 300 | C29: 300 | D29: 400 | E29: 400 | F29: 500 | G29: 500 | H29: 500 | I29: 500 | J29: 700 | K29: 700 | L29: 700 | M29: 700 | N29: =SUM(B29:M29) -> 6200
A30: CAPEX một lần | B30: 8000 | C30: 0 | D30: 0 | E30: 0 | F30: 0 | G30: 0 | H30: 0 | I30: 0 | J30: 0 | K30: 0 | L30: 0 | M30: 0 | N30: =SUM(B30:M30) -> 8000
A31: Insurance fund 5% DT | B31: =B23*0.05 -> 55 | C31: =C23*0.05 -> 109.45 | D31: =D23*0.05 -> 189.9 | E31: =E23*0.05 -> 280.1 | F31: =F23*0.05 -> 357.01667 | G31: =G23*0.05 -> 464.31667 | H31: =H23*0.05 -> 530.96667 | I31: =I23*0.05 -> 633.28333 | ... M31: =M23*0.05 -> 1070.5 | N31: =SUM(B31:M31) -> 6147.85
A32: TỔNG CHI PHÍ | B32: =SUM(B25:B31) -> 9155 | C32: =SUM(C25:C31) -> 1209.45 | D32: =SUM(D25:D31) -> 3089.9 | E32: =SUM(E25:E31) -> 3180.1 | F32: =SUM(F25:F31) -> 5057.0167 | G32: =SUM(G25:G31) -> 5164.3167 | H32: =SUM(H25:H31) -> 5230.9667 | I32: =SUM(I25:I31) -> 5333.2833 | ... M32: =SUM(M25:M31) -> 6970.5 | N32: =SUM(B32:M32) -> 64547.85
A34: LỢI NHUẬN THÁNG | B34: =B23-B32 -> -8055 | C34: =C23-C32 -> 979.55 | D34: =D23-D32 -> 708.1 | E34: =E23-E32 -> 2421.9 | F34: =F23-F32 -> 2083.3167 | G34: =G23-G32 -> 4122.0167 | H34: =H23-H32 -> 5388.3667 | I34: =I23-I32 -> 7332.3833 | ... M34: =M23-M32 -> 14439.5 | N34: =B34+SUM(C34:M34) -> 58409.15
A35: LUỸ KẾ | B35: =B34 -> -8055 | C35: =B35+C34 -> -7075.45 | D35: =C35+D34 -> -6367.35 | E35: =D35+E34 -> -3945.45 | F35: =E35+F34 -> -1862.1333 | G35: =F35+G34 -> 2259.8833 | H35: =G35+H34 -> 7648.25 | I35: =H35+I34 -> 14980.633 | J35: =I35+J34 -> 22882.867 | ... M35: =L35+M34 -> 58409.15
